LICENSE
MANIFEST.in
README.md
setup.py
pywatcher/__init__.py
pywatcher/command.py
pywatcher/pywatcher.py
pywatcher.egg-info/PKG-INFO
pywatcher.egg-info/SOURCES.txt
pywatcher.egg-info/dependency_links.txt
pywatcher.egg-info/entry_points.txt
pywatcher.egg-info/requires.txt
pywatcher.egg-info/top_level.txt