Metadata-Version: 1.0
Name: pywatcher
Version: 0.4.0
Summary: monitor file and reload process. like gulp watch.
Home-page: https://github.com/denzow/pywatcher
Author: denzow
Author-email: denzow@gmail.com
License: MIT License
